leanixpy_az/__init__.py
leanixpy_az/auth.py
leanixpy_az/graphql.py
leanix_az_py-0.0.6.dist-info/LICENSE
leanix_az_py-0.0.6.dist-info/METADATA
leanix_az_py-0.0.6.dist-info/WHEEL
leanix_az_py-0.0.6.dist-info/top_level.txt
leanix_az_py-0.0.6.dist-info/RECORD
