Metadata-Version: 2.1
Name: leanix-az-py
Version: 0.0.6
Summary: Functionality to support the development of Azure Functions
Author: Felix Jeske
Author-email: felix.jeske@leanix.net
Classifier: Development Status :: 1 - Planning
Classifier: Intended Audience :: Developers
Classifier: License :: OSI Approved :: MIT License
Classifier: Programming Language :: Python :: 3
License-File: LICENSE
Requires-Dist: requests
